sensirion_i2c_sdp/__init__.py
sensirion_i2c_sdp/version.py
sensirion_i2c_sdp/sdp/__init__.py
sensirion_i2c_sdp/sdp/commands.py
sensirion_i2c_sdp/sdp/device.py
sensirion_i2c_sdp/sdp/response_types.py
sensirion_i2c_sdp-0.1.1.dist-info/LICENSE
sensirion_i2c_sdp-0.1.1.dist-info/METADATA
sensirion_i2c_sdp-0.1.1.dist-info/WHEEL
sensirion_i2c_sdp-0.1.1.dist-info/top_level.txt
sensirion_i2c_sdp-0.1.1.dist-info/RECORD
